dstr_probability/Binomialdistribution.py
dstr_probability/Gaussiandistribution.py
dstr_probability/Generaldistribution.py
dstr_probability/__init__.py
dstr_probability-1.0.dist-info/DESCRIPTION.rst
dstr_probability-1.0.dist-info/METADATA
dstr_probability-1.0.dist-info/RECORD
dstr_probability-1.0.dist-info/WHEEL
dstr_probability-1.0.dist-info/metadata.json
dstr_probability-1.0.dist-info/top_level.txt
