Metadata-Version: 2.0
Name: dstr-probability
Version: 1.0
Summary: Gaussian and Binomial distributions
Home-page: UNKNOWN
Author: Ali Eren
Author-email: alieren.85@gmail.com
License: UNKNOWN
Platform: UNKNOWN
